README.rst
setup.cfg
setup.py
bullhorn_interface/__init__.py
bullhorn_interface/api.py
bullhorn_interface/helpers.py
bullhorn_interface/tests.py
bullhorn_interface/wrappers.py
bullhorn_interface.egg-info/PKG-INFO
bullhorn_interface.egg-info/SOURCES.txt
bullhorn_interface.egg-info/dependency_links.txt
bullhorn_interface.egg-info/requires.txt
bullhorn_interface.egg-info/top_level.txt
example_applications/__init__.py
example_applications/bullhorn_call.py
example_applications/call_filewise.py