Metadata-Version: 1.2
Name: bullhorn-interface
Version: 2.0.13.dev0
Summary: A simple Python package to facilitate interactions with the Bullhorn REST API
Home-page: https://github.com/jjorissen52/bullhorn_interface
Author: John-Paul Jorissen
Author-email: jjorissen52@gmail.com
License: Apache
Keywords: Bullhorn Python API RESTAPI
Platform: UNKNOWN
Classifier: Development Status :: 3 - Alpha
Classifier: Intended Audience :: Developers
Classifier: Programming Language :: Python :: 3.6
Classifier: Operating System :: Microsoft :: Windows :: Windows 10
Classifier: Operating System :: POSIX :: Linux
Classifier: Topic :: Office/Business
Classifier: License :: OSI Approved :: Apache Software License
Classifier: Programming Language :: Python :: 3.6
Requires-Python: >=3.6
